[{"model": "viewer.movie", "pk": 7, "fields": {"title": "Toy story 3", "genre": 2, "rating": 2, "released": "2021-10-10", "description": "A new movie. By. By!", "created": "2021-10-17T07:07:07.209Z"}}, {"model": "viewer.movie", "pk": 8, "fields": {"title": "The Silence", "genre": 7, "rating": 5, "released": "2009-09-09", "description": "Bla. Bla. Bla!", "created": "2021-10-17T07:12:12.063Z"}}, {"model": "viewer.movie", "pk": 9, "fields": {"title": "The new Movie", "genre": 8, "rating": 8, "released": "2018-09-10", "description": "Testing. A new movie. . . ", "created": "2021-10-17T07:33:53.441Z"}}, {"model": "viewer.movie", "pk": 10, "fields": {"title": "The new Movie", "genre": 8, "rating": 8, "released": "2018-09-10", "description": "Testing. A new movie. . . ", "created": "2021-10-17T07:39:14.154Z"}}, {"model": "viewer.movie", "pk": 11, "fields": {"title": "The new Movie", "genre": 2, "rating": 4, "released": "2018-09-10", "description": "Test description. . . . . . ", "created": "2021-10-17T09:51:20.678Z"}}, {"model": "viewer.movie", "pk": 12, "fields": {"title": "Disney", "genre": 6, "rating": 2, "released": "2018-09-10", "description": "My description. . . . . ", "created": "2021-10-17T09:54:07.338Z"}}, {"model": "viewer.movie", "pk": 13, "fields": {"title": "Start Wars", "genre": 6, "rating": 7, "released": "2018-09-10", "description": "This is a new movie. . . . . ", "created": "2021-10-17T10:43:14.230Z"}}, {"model": "viewer.movie", "pk": 14, "fields": {"title": "Start Wars 9", "genre": 6, "rating": 7, "released": "2018-09-10", "description": "This is a new movie. . . . ", "created": "2021-10-17T10:52:18.612Z"}}, {"model": "viewer.movie", "pk": 15, "fields": {"title": "Nobody", "genre": 2, "rating": 3, "released": "2018-09-10", "description": ". . . . . ", "created": "2021-10-23T06:10:39.759Z"}}]